MANIFEST.in
setup.py
pypmserver/__init__.py
pypmserver/background_tasks.py
pypmserver/context.py
pypmserver/index.py
pypmserver/info.py
pypmserver/main.py
pypmserver/model_user.py
pypmserver/server.py
pypmserver/support_xmlrpc.py
pypmserver/task_cleaner.py
pypmserver/upload.py
pypmserver.egg-info/PKG-INFO
pypmserver.egg-info/SOURCES.txt
pypmserver.egg-info/dependency_links.txt
pypmserver.egg-info/entry_points.txt
pypmserver.egg-info/requires.txt
pypmserver.egg-info/top_level.txt
pypmserver.egg-info/zip-safe
pypmserver/templates/busy.html
pypmserver/templates/index.html