Metadata-Version: 1.0
Name: pypmserver
Version: 0.1.67
Summary: pypmserver v. 0.1.66
